permify/__init__.py
permify/api_client.py
permify/api_response.py
permify/configuration.py
permify/exceptions.py
permify/py.typed
permify/rest.py
permify/api/__init__.py
permify/api/bundle_api.py
permify/api/data_api.py
permify/api/permission_api.py
permify/api/schema_api.py
permify/api/tenancy_api.py
permify/api/watch_api.py
permify/models/__init__.py
permify/models/abstract_type.py
permify/models/any.py
permify/models/argument.py
permify/models/attribute.py
permify/models/attribute_definition.py
permify/models/attribute_filter.py
permify/models/attribute_read_request_metadata.py
permify/models/attribute_read_response.py
permify/models/attribute_type.py
permify/models/bulk_check_body.py
permify/models/bundle_delete_body.py
permify/models/bundle_delete_response.py
permify/models/bundle_read_body.py
permify/models/bundle_read_response.py
permify/models/bundle_run_response.py
permify/models/bundle_write_body.py
permify/models/bundle_write_response.py
permify/models/check_body.py
permify/models/check_result.py
permify/models/checked_expr.py
permify/models/child.py
permify/models/component.py
permify/models/comprehension.py
permify/models/computed_attribute.py
permify/models/computed_user_set.py
permify/models/constant.py
permify/models/context.py
permify/models/create_list.py
permify/models/create_struct.py
permify/models/data_bundle.py
permify/models/data_change.py
permify/models/data_change_operation.py
permify/models/data_changes.py
permify/models/data_delete_body.py
permify/models/data_delete_response.py
permify/models/data_write_body.py
permify/models/data_write_request_metadata.py
permify/models/data_write_response.py
permify/models/delete_relationships_body.py
permify/models/entity.py
permify/models/entity_definition.py
permify/models/entity_definition_reference.py
permify/models/entity_filter.py
permify/models/entry.py
permify/models/expand_leaf.py
permify/models/expand_tree_node.py
permify/models/expand_tree_node_operation.py
permify/models/expr.py
permify-1.5.4.dist-info/licenses/LICENCE
permify-1.5.4.dist-info/METADATA
permify-1.5.4.dist-info/WHEEL
permify-1.5.4.dist-info/top_level.txt
permify-1.5.4.dist-info/RECORD
