Metadata-Version: 2.4
Name: permify
Version: 1.5.4
Summary: Permify API
Home-page: https://github.com/Permify/permify-python
Author: API Support
Author-email: hello@permify.co
License: AGPL-3.0 license
Keywords: OpenAPI,OpenAPI-Generator,Permify API
License-File: LICENCE
Requires-Dist: urllib3<2.1.0,>=1.25.3
Requires-Dist: python-dateutil
Requires-Dist: pydantic>=2
Requires-Dist: typing-extensions>=4.7.1
Dynamic: author
Dynamic: author-email
Dynamic: description
Dynamic: description-content-type
Dynamic: home-page
Dynamic: keywords
Dynamic: license
Dynamic: license-file
Dynamic: requires-dist
Dynamic: summary
